pyramid_math/__init__.py
pyramid_math/__main__.py
pyramid_math/constants.py
pyramid_math/database.py
pyramid_math/geometry.py
pyramid_math/pyramid.py
pyramid_math-0.0.5.dist-info/LICENSE
pyramid_math-0.0.5.dist-info/METADATA
pyramid_math-0.0.5.dist-info/WHEEL
pyramid_math-0.0.5.dist-info/top_level.txt
pyramid_math-0.0.5.dist-info/RECORD
