Metadata-Version: 2.2
Name: pyramid_math
Version: 0.0.5
Summary: A package for performing mathematical calculations on pyramids.
Home-page: https://github.com/ishanoshada/pyramid-math
Author: Ishan Oshada
Author-email: ishan.kodithuwakku.official@email.com
Classifier: Programming Language :: Python :: 3
Classifier: License :: OSI Approved :: MIT License
Classifier: Operating System :: OS Independent
License-File: LICENSE
Requires-Dist: numpy
Dynamic: author
Dynamic: author-email
Dynamic: classifier
Dynamic: description
Dynamic: description-content-type
Dynamic: home-page
Dynamic: requires-dist
Dynamic: summary
